beetsplug/__init__.py
beetsplug/lidarrfields.py
beets_lidarr_fields-1.1.2.dist-info/LICENSE
beets_lidarr_fields-1.1.2.dist-info/METADATA
beets_lidarr_fields-1.1.2.dist-info/WHEEL
beets_lidarr_fields-1.1.2.dist-info/top_level.txt
beets_lidarr_fields-1.1.2.dist-info/RECORD
