Metadata-Version: 2.1
Name: beets-lidarr-fields
Version: 1.1.2
Summary: Beets plugin that defines some useful template fields to customize your path formats in a more lidarr way.
Home-page: https://github.com/rafaelparente/beets-lidarr-fields
Author: Rafael Parente
Author-email: rafaelp.dev@gmail.com
License: MIT
Platform: UNKNOWN
Classifier: Development Status :: 5 - Production/Stable
Classifier: Environment :: Plugins
Classifier: License :: OSI Approved :: MIT License
Classifier: Programming Language :: Python
Classifier: Programming Language :: Python :: 3
Classifier: Programming Language :: Python :: 3.4
Classifier: Programming Language :: Python :: Implementation :: CPython
Classifier: Programming Language :: Python :: Implementation :: PyPy
Classifier: Topic :: Multimedia :: Sound/Audio
Requires-Python: >=3.4.0
Requires-Dist: beets
Requires-Dist: musicbrainzngs
